{
  "ptID": 29,
  "gender": "F",
  "age": 49,
  "race": "White",
  "ethnicity": "Not Hispanic or Latino",
  "height": 165.0,
  "weight": 104.5,
  "davDiabetes": 20.8,
  "insulinModality": "Pump",
  "numSevHypo": "0",
  "hgmReadAvg": 3,
  "eduCareGvrP": "Subject",
  "eduCareGvrPEdu": "Associates",
  "date": "2000-08-31 10:34:00",
  "txGroup": "Control",
  "subStudyGrp": "Primary",
  "measurements": [
    {
      "deviceDtTm": "2000-08-24 20:41:24",
      "glucose": 108
    },
    {
      "deviceDtTm": "2000-08-24 20:51:28",
      "glucose": 106
    },
    {
      "deviceDtTm": "2000-08-25 01:01:41",
      "glucose": 162
    },
    {
      "deviceDtTm": "2000-08-25 01:11:42",
      "glucose": 165
    },
    {
      "deviceDtTm": "2000-08-25 01:21:48",
      "glucose": 169
    },
    {
      "deviceDtTm": "2000-08-25 01:31:40",
      "glucose": 170
    },
    {
      "deviceDtTm": "2000-08-25 01:41:47",
      "glucose": 171
    },
    {
      "deviceDtTm": "2000-08-25 01:51:46",
      "glucose": 174
    },
    {
      "deviceDtTm": "2000-08-25 02:01:47",
      "glucose": 189
    },
    {
      "deviceDtTm": "2000-08-25 02:11:42",
      "glucose": 195
    },
    {
      "deviceDtTm": "2000-08-25 02:21:48",
      "glucose": 196
    },
    {
      "deviceDtTm": "2000-08-25 02:31:51",
      "glucose": 198
    },
    {
      "deviceDtTm": "2000-08-25 02:41:51",
      "glucose": 200
    },
    {
      "deviceDtTm": "2000-08-25 02:51:51",
      "glucose": 205
    },
    {
      "deviceDtTm": "2000-08-25 03:01:48",
      "glucose": 208
    },
    {
      "deviceDtTm": "2000-08-25 03:11:51",
      "glucose": 207
    },
    {
      "deviceDtTm": "2000-08-25 03:21:49",
      "glucose": 211
    },
    {
      "deviceDtTm": "2000-08-25 03:31:55",
      "glucose": 199
    },
    {
      "deviceDtTm": "2000-08-25 03:41:52",
      "glucose": 187
    },
    {
      "deviceDtTm": "2000-08-25 03:51:48",
      "glucose": 189
    },
    {
      "deviceDtTm": "2000-08-25 04:01:49",
      "glucose": 202
    },
    {
      "deviceDtTm": "2000-08-25 04:11:57",
      "glucose": 201
    },
    {
      "deviceDtTm": "2000-08-25 04:21:49",
      "glucose": 210
    },
    {
      "deviceDtTm": "2000-08-25 04:31:53",
      "glucose": 220
    },
    {
      "deviceDtTm": "2000-08-25 04:41:53",
      "glucose": 225
    },
    {
      "deviceDtTm": "2000-08-25 04:51:53",
      "glucose": 229
    },
    {
      "deviceDtTm": "2000-08-25 05:01:55",
      "glucose": 222
    },
    {
      "deviceDtTm": "2000-08-25 05:11:59",
      "glucose": 214
    },
    {
      "deviceDtTm": "2000-08-25 05:22:01",
      "glucose": 212
    },
    {
      "deviceDtTm": "2000-08-25 05:31:57",
      "glucose": 221
    },
    {
      "deviceDtTm": "2000-08-25 05:42:02",
      "glucose": 209
    },
    {
      "deviceDtTm": "2000-08-25 05:51:56",
      "glucose": 215
    },
    {
      "deviceDtTm": "2000-08-25 06:02:03",
      "glucose": 217
    },
    {
      "deviceDtTm": "2000-08-25 06:11:58",
      "glucose": 231
    },
    {
      "deviceDtTm": "2000-08-25 06:21:59",
      "glucose": 234
    },
    {
      "deviceDtTm": "2000-08-25 06:32:05",
      "glucose": 216
    },
    {
      "deviceDtTm": "2000-08-25 06:41:57",
      "glucose": 207
    },
    {
      "deviceDtTm": "2000-08-25 06:52:06",
      "glucose": 205
    },
    {
      "deviceDtTm": "2000-08-25 07:02:02",
      "glucose": 209
    },
    {
      "deviceDtTm": "2000-08-25 07:11:59",
      "glucose": 224
    },
    {
      "deviceDtTm": "2000-08-25 07:22:08",
      "glucose": 241
    },
    {
      "deviceDtTm": "2000-08-25 07:32:06",
      "glucose": 244
    },
    {
      "deviceDtTm": "2000-08-25 07:42:06",
      "glucose": 241
    },
    {
      "deviceDtTm": "2000-08-25 07:52:01",
      "glucose": 236
    },
    {
      "deviceDtTm": "2000-08-25 08:02:02",
      "glucose": 228
    },
    {
      "deviceDtTm": "2000-08-25 08:12:09",
      "glucose": 208
    },
    {
      "deviceDtTm": "2000-08-25 08:22:03",
      "glucose": 186
    },
    {
      "deviceDtTm": "2000-08-25 08:32:07",
      "glucose": 157
    },
    {
      "deviceDtTm": "2000-08-25 08:42:11",
      "glucose": 136
    },
    {
      "deviceDtTm": "2000-08-25 08:52:11",
      "glucose": 111
    },
    {
      "deviceDtTm": "2000-08-25 09:02:14",
      "glucose": 98
    },
    {
      "deviceDtTm": "2000-08-25 09:12:09",
      "glucose": 88
    },
    {
      "deviceDtTm": "2000-08-25 09:22:07",
      "glucose": 80
    },
    {
      "deviceDtTm": "2000-08-25 09:32:14",
      "glucose": 79
    },
    {
      "deviceDtTm": "2000-08-25 09:42:14",
      "glucose": 78
    },
    {
      "deviceDtTm": "2000-08-25 09:52:11",
      "glucose": 80
    },
    {
      "deviceDtTm": "2000-08-25 10:02:16",
      "glucose": 80
    },
    {
      "deviceDtTm": "2000-08-25 10:12:14",
      "glucose": 80
    },
    {
      "deviceDtTm": "2000-08-25 10:22:14",
      "glucose": 76
    },
    {
      "deviceDtTm": "2000-08-25 10:32:12",
      "glucose": 75
    },
    {
      "deviceDtTm": "2000-08-25 10:42:18",
      "glucose": 77
    },
    {
      "deviceDtTm": "2000-08-25 10:52:16",
      "glucose": 80
    },
    {
      "deviceDtTm": "2000-08-25 11:02:18",
      "glucose": 86
    },
    {
      "deviceDtTm": "2000-08-25 11:12:14",
      "glucose": 94
    },
    {
      "deviceDtTm": "2000-08-25 11:22:13",
      "glucose": 99
    },
    {
      "deviceDtTm": "2000-08-25 11:32:17",
      "glucose": 104
    },
    {
      "deviceDtTm": "2000-08-25 11:42:19",
      "glucose": 109
    },
    {
      "deviceDtTm": "2000-08-25 11:52:22",
      "glucose": 118
    },
    {
      "deviceDtTm": "2000-08-25 12:02:23",
      "glucose": 126
    },
    {
      "deviceDtTm": "2000-08-25 12:12:21",
      "glucose": 131
    },
    {
      "deviceDtTm": "2000-08-25 12:22:26",
      "glucose": 137
    },
    {
      "deviceDtTm": "2000-08-25 12:32:19",
      "glucose": 147
    },
    {
      "deviceDtTm": "2000-08-25 12:42:25",
      "glucose": 163
    },
    {
      "deviceDtTm": "2000-08-25 12:52:19",
      "glucose": 173
    },
    {
      "deviceDtTm": "2000-08-25 13:02:23",
      "glucose": 177
    },
    {
      "deviceDtTm": "2000-08-25 13:12:29",
      "glucose": 197
    },
    {
      "deviceDtTm": "2000-08-25 13:22:23",
      "glucose": 201
    },
    {
      "deviceDtTm": "2000-08-25 13:32:25",
      "glucose": 196
    },
    {
      "deviceDtTm": "2000-08-25 13:42:24",
      "glucose": 189
    },
    {
      "deviceDtTm": "2000-08-25 13:52:27",
      "glucose": 185
    },
    {
      "deviceDtTm": "2000-08-25 14:02:26",
      "glucose": 184
    },
    {
      "deviceDtTm": "2000-08-25 14:12:29",
      "glucose": 177
    },
    {
      "deviceDtTm": "2000-08-25 14:22:31",
      "glucose": 164
    },
    {
      "deviceDtTm": "2000-08-25 14:32:30",
      "glucose": 152
    },
    {
      "deviceDtTm": "2000-08-25 14:42:27",
      "glucose": 147
    },
    {
      "deviceDtTm": "2000-08-25 14:52:32",
      "glucose": 153
    },
    {
      "deviceDtTm": "2000-08-25 15:02:27",
      "glucose": 161
    },
    {
      "deviceDtTm": "2000-08-25 15:12:32",
      "glucose": 170
    },
    {
      "deviceDtTm": "2000-08-25 15:22:32",
      "glucose": 181
    },
    {
      "deviceDtTm": "2000-08-25 15:32:32",
      "glucose": 194
    },
    {
      "deviceDtTm": "2000-08-25 15:42:32",
      "glucose": 197
    },
    {
      "deviceDtTm": "2000-08-25 15:52:30",
      "glucose": 204
    },
    {
      "deviceDtTm": "2000-08-25 16:02:34",
      "glucose": 207
    },
    {
      "deviceDtTm": "2000-08-25 16:12:31",
      "glucose": 206
    },
    {
      "deviceDtTm": "2000-08-25 16:22:37",
      "glucose": 204
    },
    {
      "deviceDtTm": "2000-08-25 16:32:39",
      "glucose": 209
    },
    {
      "deviceDtTm": "2000-08-25 16:42:37",
      "glucose": 210
    },
    {
      "deviceDtTm": "2000-08-25 16:52:35",
      "glucose": 210
    },
    {
      "deviceDtTm": "2000-08-25 17:02:33",
      "glucose": 213
    },
    {
      "deviceDtTm": "2000-08-25 17:12:35",
      "glucose": 214
    },
    {
      "deviceDtTm": "2000-08-25 17:22:40",
      "glucose": 212
    },
    {
      "deviceDtTm": "2000-08-25 17:32:44",
      "glucose": 214
    },
    {
      "deviceDtTm": "2000-08-25 17:42:36",
      "glucose": 217
    },
    {
      "deviceDtTm": "2000-08-25 17:52:45",
      "glucose": 222
    },
    {
      "deviceDtTm": "2000-08-25 18:02:38",
      "glucose": 227
    },
    {
      "deviceDtTm": "2000-08-25 18:12:43",
      "glucose": 226
    },
    {
      "deviceDtTm": "2000-08-25 18:22:43",
      "glucose": 228
    },
    {
      "deviceDtTm": "2000-08-25 18:32:40",
      "glucose": 245
    },
    {
      "deviceDtTm": "2000-08-25 18:42:39",
      "glucose": 246
    },
    {
      "deviceDtTm": "2000-08-25 18:52:45",
      "glucose": 248
    },
    {
      "deviceDtTm": "2000-08-25 19:02:44",
      "glucose": 245
    },
    {
      "deviceDtTm": "2000-08-25 19:12:49",
      "glucose": 240
    },
    {
      "deviceDtTm": "2000-08-25 19:22:43",
      "glucose": 213
    },
    {
      "deviceDtTm": "2000-08-25 19:32:46",
      "glucose": 191
    },
    {
      "deviceDtTm": "2000-08-25 19:42:48",
      "glucose": 182
    },
    {
      "deviceDtTm": "2000-08-25 19:52:46",
      "glucose": 188
    },
    {
      "deviceDtTm": "2000-08-25 20:02:53",
      "glucose": 184
    },
    {
      "deviceDtTm": "2000-08-25 20:12:44",
      "glucose": 180
    },
    {
      "deviceDtTm": "2000-08-25 20:22:45",
      "glucose": 170
    },
    {
      "deviceDtTm": "2000-08-25 20:32:51",
      "glucose": 172
    },
    {
      "deviceDtTm": "2000-08-25 20:42:53",
      "glucose": 168
    },
    {
      "deviceDtTm": "2000-08-25 20:52:47",
      "glucose": 164
    },
    {
      "deviceDtTm": "2000-08-25 21:02:47",
      "glucose": 155
    },
    {
      "deviceDtTm": "2000-08-25 21:12:48",
      "glucose": 155
    },
    {
      "deviceDtTm": "2000-08-25 21:22:54",
      "glucose": 155
    },
    {
      "deviceDtTm": "2000-08-25 21:32:56",
      "glucose": 142
    },
    {
      "deviceDtTm": "2000-08-25 21:42:50",
      "glucose": 126
    },
    {
      "deviceDtTm": "2000-08-25 21:52:56",
      "glucose": 137
    },
    {
      "deviceDtTm": "2000-08-25 22:02:58",
      "glucose": 153
    },
    {
      "deviceDtTm": "2000-08-25 22:12:56",
      "glucose": 151
    },
    {
      "deviceDtTm": "2000-08-25 22:22:55",
      "glucose": 148
    },
    {
      "deviceDtTm": "2000-08-25 22:32:57",
      "glucose": 160
    },
    {
      "deviceDtTm": "2000-08-25 22:43:02",
      "glucose": 175
    },
    {
      "deviceDtTm": "2000-08-25 22:52:54",
      "glucose": 176
    },
    {
      "deviceDtTm": "2000-08-25 23:03:01",
      "glucose": 188
    },
    {
      "deviceDtTm": "2000-08-25 23:13:00",
      "glucose": 191
    },
    {
      "deviceDtTm": "2000-08-25 23:23:01",
      "glucose": 194
    },
    {
      "deviceDtTm": "2000-08-25 23:32:56",
      "glucose": 200
    },
    {
      "deviceDtTm": "2000-08-25 23:43:02",
      "glucose": 221
    },
    {
      "deviceDtTm": "2000-08-25 23:53:05",
      "glucose": 221
    },
    {
      "deviceDtTm": "2000-08-26 00:03:05",
      "glucose": 217
    },
    {
      "deviceDtTm": "2000-08-26 00:13:05",
      "glucose": 227
    },
    {
      "deviceDtTm": "2000-08-26 00:23:02",
      "glucose": 249
    },
    {
      "deviceDtTm": "2000-08-26 00:33:05",
      "glucose": 249
    },
    {
      "deviceDtTm": "2000-08-26 00:43:03",
      "glucose": 245
    },
    {
      "deviceDtTm": "2000-08-26 00:53:09",
      "glucose": 242
    },
    {
      "deviceDtTm": "2000-08-26 01:03:06",
      "glucose": 236
    },
    {
      "deviceDtTm": "2000-08-26 01:13:02",
      "glucose": 229
    },
    {
      "deviceDtTm": "2000-08-26 01:23:04",
      "glucose": 225
    },
    {
      "deviceDtTm": "2000-08-26 01:33:12",
      "glucose": 221
    },
    {
      "deviceDtTm": "2000-08-26 01:43:03",
      "glucose": 211
    },
    {
      "deviceDtTm": "2000-08-26 01:53:07",
      "glucose": 206
    },
    {
      "deviceDtTm": "2000-08-26 02:03:07",
      "glucose": 206
    },
    {
      "deviceDtTm": "2000-08-26 02:13:07",
      "glucose": 205
    },
    {
      "deviceDtTm": "2000-08-26 02:23:09",
      "glucose": 201
    },
    {
      "deviceDtTm": "2000-08-26 02:33:13",
      "glucose": 199
    },
    {
      "deviceDtTm": "2000-08-26 02:43:15",
      "glucose": 195
    },
    {
      "deviceDtTm": "2000-08-26 02:53:11",
      "glucose": 185
    },
    {
      "deviceDtTm": "2000-08-26 03:03:16",
      "glucose": 183
    },
    {
      "deviceDtTm": "2000-08-26 03:13:10",
      "glucose": 181
    },
    {
      "deviceDtTm": "2000-08-26 03:23:17",
      "glucose": 177
    },
    {
      "deviceDtTm": "2000-08-26 03:33:13",
      "glucose": 170
    },
    {
      "deviceDtTm": "2000-08-26 03:43:13",
      "glucose": 154
    },
    {
      "deviceDtTm": "2000-08-26 03:53:19",
      "glucose": 148
    },
    {
      "deviceDtTm": "2000-08-26 04:03:11",
      "glucose": 140
    },
    {
      "deviceDtTm": "2000-08-26 04:13:20",
      "glucose": 142
    },
    {
      "deviceDtTm": "2000-08-26 04:23:17",
      "glucose": 144
    },
    {
      "deviceDtTm": "2000-08-26 04:33:13",
      "glucose": 145
    },
    {
      "deviceDtTm": "2000-08-26 04:43:22",
      "glucose": 139
    },
    {
      "deviceDtTm": "2000-08-26 04:53:20",
      "glucose": 136
    },
    {
      "deviceDtTm": "2000-08-26 05:03:20",
      "glucose": 125
    },
    {
      "deviceDtTm": "2000-08-26 05:13:15",
      "glucose": 122
    },
    {
      "deviceDtTm": "2000-08-26 05:23:16",
      "glucose": 109
    },
    {
      "deviceDtTm": "2000-08-26 05:33:23",
      "glucose": 100
    },
    {
      "deviceDtTm": "2000-08-26 05:43:17",
      "glucose": 104
    },
    {
      "deviceDtTm": "2000-08-26 05:53:21",
      "glucose": 97
    },
    {
      "deviceDtTm": "2000-08-26 06:03:25",
      "glucose": 89
    },
    {
      "deviceDtTm": "2000-08-26 06:13:25",
      "glucose": 87
    },
    {
      "deviceDtTm": "2000-08-26 06:23:28",
      "glucose": 85
    },
    {
      "deviceDtTm": "2000-08-26 06:33:23",
      "glucose": 81
    },
    {
      "deviceDtTm": "2000-08-26 06:43:21",
      "glucose": 77
    },
    {
      "deviceDtTm": "2000-08-26 06:53:28",
      "glucose": 74
    },
    {
      "deviceDtTm": "2000-08-26 07:03:28",
      "glucose": 63
    },
    {
      "deviceDtTm": "2000-08-26 07:13:25",
      "glucose": 67
    },
    {
      "deviceDtTm": "2000-08-26 07:23:30",
      "glucose": 70
    },
    {
      "deviceDtTm": "2000-08-26 07:33:28",
      "glucose": 72
    },
    {
      "deviceDtTm": "2000-08-26 07:43:28",
      "glucose": 75
    },
    {
      "deviceDtTm": "2000-08-26 07:53:26",
      "glucose": 98
    },
    {
      "deviceDtTm": "2000-08-26 08:03:32",
      "glucose": 132
    },
    {
      "deviceDtTm": "2000-08-26 08:13:30",
      "glucose": 144
    },
    {
      "deviceDtTm": "2000-08-26 08:23:32",
      "glucose": 140
    },
    {
      "deviceDtTm": "2000-08-26 08:33:28",
      "glucose": 118
    },
    {
      "deviceDtTm": "2000-08-26 08:43:27",
      "glucose": 103
    },
    {
      "deviceDtTm": "2000-08-26 08:53:31",
      "glucose": 92
    },
    {
      "deviceDtTm": "2000-08-26 09:03:33",
      "glucose": 83
    },
    {
      "deviceDtTm": "2000-08-26 09:13:36",
      "glucose": 78
    },
    {
      "deviceDtTm": "2000-08-26 09:23:37",
      "glucose": 76
    },
    {
      "deviceDtTm": "2000-08-26 09:33:35",
      "glucose": 75
    },
    {
      "deviceDtTm": "2000-08-26 09:43:40",
      "glucose": 73
    },
    {
      "deviceDtTm": "2000-08-26 09:53:34",
      "glucose": 71
    },
    {
      "deviceDtTm": "2000-08-26 10:03:39",
      "glucose": 70
    },
    {
      "deviceDtTm": "2000-08-26 10:13:33",
      "glucose": 71
    },
    {
      "deviceDtTm": "2000-08-26 10:23:37",
      "glucose": 71
    },
    {
      "deviceDtTm": "2000-08-26 10:33:43",
      "glucose": 74
    },
    {
      "deviceDtTm": "2000-08-26 10:43:37",
      "glucose": 77
    },
    {
      "deviceDtTm": "2000-08-26 10:53:39",
      "glucose": 79
    },
    {
      "deviceDtTm": "2000-08-26 11:03:38",
      "glucose": 85
    },
    {
      "deviceDtTm": "2000-08-26 11:13:41",
      "glucose": 89
    },
    {
      "deviceDtTm": "2000-08-26 11:23:40",
      "glucose": 93
    },
    {
      "deviceDtTm": "2000-08-26 11:33:43",
      "glucose": 98
    },
    {
      "deviceDtTm": "2000-08-26 11:43:45",
      "glucose": 106
    },
    {
      "deviceDtTm": "2000-08-26 11:53:44",
      "glucose": 108
    },
    {
      "deviceDtTm": "2000-08-26 12:03:41",
      "glucose": 110
    },
    {
      "deviceDtTm": "2000-08-26 12:13:46",
      "glucose": 114
    },
    {
      "deviceDtTm": "2000-08-26 12:23:41",
      "glucose": 114
    },
    {
      "deviceDtTm": "2000-08-26 12:33:46",
      "glucose": 112
    },
    {
      "deviceDtTm": "2000-08-26 12:43:46",
      "glucose": 130
    },
    {
      "deviceDtTm": "2000-08-26 12:53:47",
      "glucose": 146
    },
    {
      "deviceDtTm": "2000-08-26 13:03:46",
      "glucose": 153
    },
    {
      "deviceDtTm": "2000-08-26 13:13:44",
      "glucose": 156
    },
    {
      "deviceDtTm": "2000-08-26 13:23:48",
      "glucose": 157
    },
    {
      "deviceDtTm": "2000-08-26 13:33:45",
      "glucose": 164
    },
    {
      "deviceDtTm": "2000-08-26 13:43:51",
      "glucose": 167
    },
    {
      "deviceDtTm": "2000-08-26 13:53:53",
      "glucose": 167
    },
    {
      "deviceDtTm": "2000-08-26 14:03:51",
      "glucose": 162
    },
    {
      "deviceDtTm": "2000-08-26 14:13:49",
      "glucose": 160
    },
    {
      "deviceDtTm": "2000-08-26 14:23:47",
      "glucose": 168
    },
    {
      "deviceDtTm": "2000-08-26 14:33:49",
      "glucose": 175
    },
    {
      "deviceDtTm": "2000-08-26 14:43:54",
      "glucose": 184
    },
    {
      "deviceDtTm": "2000-08-26 14:53:58",
      "glucose": 190
    },
    {
      "deviceDtTm": "2000-08-26 15:03:51",
      "glucose": 197
    },
    {
      "deviceDtTm": "2000-08-26 15:13:59",
      "glucose": 200
    },
    {
      "deviceDtTm": "2000-08-26 15:23:52",
      "glucose": 201
    },
    {
      "deviceDtTm": "2000-08-26 15:33:57",
      "glucose": 202
    },
    {
      "deviceDtTm": "2000-08-26 15:43:57",
      "glucose": 202
    },
    {
      "deviceDtTm": "2000-08-26 15:53:54",
      "glucose": 203
    },
    {
      "deviceDtTm": "2000-08-26 16:03:53",
      "glucose": 202
    },
    {
      "deviceDtTm": "2000-08-26 16:13:59",
      "glucose": 199
    },
    {
      "deviceDtTm": "2000-08-26 16:23:58",
      "glucose": 200
    },
    {
      "deviceDtTm": "2000-08-26 16:34:04",
      "glucose": 202
    },
    {
      "deviceDtTm": "2000-08-26 16:43:57",
      "glucose": 204
    },
    {
      "deviceDtTm": "2000-08-26 16:54:00",
      "glucose": 202
    },
    {
      "deviceDtTm": "2000-08-26 17:04:02",
      "glucose": 203
    },
    {
      "deviceDtTm": "2000-08-26 17:14:00",
      "glucose": 204
    },
    {
      "deviceDtTm": "2000-08-26 17:24:07",
      "glucose": 205
    },
    {
      "deviceDtTm": "2000-08-26 17:33:58",
      "glucose": 204
    },
    {
      "deviceDtTm": "2000-08-26 17:43:59",
      "glucose": 197
    },
    {
      "deviceDtTm": "2000-08-26 17:54:05",
      "glucose": 194
    },
    {
      "deviceDtTm": "2000-08-26 18:04:07",
      "glucose": 193
    },
    {
      "deviceDtTm": "2000-08-26 18:14:01",
      "glucose": 176
    },
    {
      "deviceDtTm": "2000-08-26 18:24:01",
      "glucose": 155
    },
    {
      "deviceDtTm": "2000-08-26 18:34:02",
      "glucose": 137
    },
    {
      "deviceDtTm": "2000-08-26 18:44:08",
      "glucose": 126
    },
    {
      "deviceDtTm": "2000-08-26 18:54:10",
      "glucose": 110
    },
    {
      "deviceDtTm": "2000-08-26 19:04:04",
      "glucose": 90
    },
    {
      "deviceDtTm": "2000-08-26 19:14:10",
      "glucose": 77
    },
    {
      "deviceDtTm": "2000-08-26 19:24:12",
      "glucose": 68
    },
    {
      "deviceDtTm": "2000-08-26 19:34:10",
      "glucose": 61
    },
    {
      "deviceDtTm": "2000-08-26 19:44:09",
      "glucose": 62
    },
    {
      "deviceDtTm": "2000-08-26 19:54:11",
      "glucose": 59
    },
    {
      "deviceDtTm": "2000-08-26 20:04:16",
      "glucose": 60
    },
    {
      "deviceDtTm": "2000-08-26 20:14:08",
      "glucose": 61
    },
    {
      "deviceDtTm": "2000-08-26 20:24:15",
      "glucose": 66
    },
    {
      "deviceDtTm": "2000-08-26 20:34:14",
      "glucose": 71
    },
    {
      "deviceDtTm": "2000-08-26 20:44:15",
      "glucose": 75
    },
    {
      "deviceDtTm": "2000-08-26 20:54:10",
      "glucose": 80
    },
    {
      "deviceDtTm": "2000-08-26 21:04:16",
      "glucose": 80
    },
    {
      "deviceDtTm": "2000-08-26 21:14:20",
      "glucose": 79
    },
    {
      "deviceDtTm": "2000-08-26 21:24:19",
      "glucose": 79
    },
    {
      "deviceDtTm": "2000-08-26 21:34:19",
      "glucose": 81
    },
    {
      "deviceDtTm": "2000-08-26 21:44:16",
      "glucose": 80
    },
    {
      "deviceDtTm": "2000-08-26 21:54:19",
      "glucose": 81
    },
    {
      "deviceDtTm": "2000-08-26 22:04:17",
      "glucose": 83
    },
    {
      "deviceDtTm": "2000-08-26 22:14:23",
      "glucose": 84
    },
    {
      "deviceDtTm": "2000-08-26 22:24:20",
      "glucose": 86
    },
    {
      "deviceDtTm": "2000-08-26 22:34:16",
      "glucose": 85
    },
    {
      "deviceDtTm": "2000-08-26 22:44:18",
      "glucose": 84
    },
    {
      "deviceDtTm": "2000-08-26 22:54:26",
      "glucose": 85
    },
    {
      "deviceDtTm": "2000-08-26 23:04:17",
      "glucose": 85
    },
    {
      "deviceDtTm": "2000-08-26 23:14:21",
      "glucose": 83
    },
    {
      "deviceDtTm": "2000-08-26 23:24:21",
      "glucose": 84
    },
    {
      "deviceDtTm": "2000-08-26 23:34:21",
      "glucose": 89
    },
    {
      "deviceDtTm": "2000-08-26 23:44:23",
      "glucose": 85
    },
    {
      "deviceDtTm": "2000-08-26 23:54:27",
      "glucose": 86
    },
    {
      "deviceDtTm": "2000-08-27 00:04:30",
      "glucose": 88
    },
    {
      "deviceDtTm": "2000-08-27 00:14:25",
      "glucose": 82
    },
    {
      "deviceDtTm": "2000-08-27 00:24:30",
      "glucose": 79
    },
    {
      "deviceDtTm": "2000-08-27 00:34:24",
      "glucose": 77
    },
    {
      "deviceDtTm": "2000-08-27 00:44:31",
      "glucose": 81
    },
    {
      "deviceDtTm": "2000-08-27 00:54:27",
      "glucose": 83
    },
    {
      "deviceDtTm": "2000-08-27 01:04:27",
      "glucose": 83
    },
    {
      "deviceDtTm": "2000-08-27 01:14:33",
      "glucose": 84
    },
    {
      "deviceDtTm": "2000-08-27 01:24:25",
      "glucose": 85
    },
    {
      "deviceDtTm": "2000-08-27 01:34:34",
      "glucose": 88
    },
    {
      "deviceDtTm": "2000-08-27 01:44:31",
      "glucose": 91
    },
    {
      "deviceDtTm": "2000-08-27 01:54:27",
      "glucose": 93
    },
    {
      "deviceDtTm": "2000-08-27 02:04:36",
      "glucose": 103
    },
    {
      "deviceDtTm": "2000-08-27 02:14:34",
      "glucose": 103
    },
    {
      "deviceDtTm": "2000-08-27 02:24:34",
      "glucose": 109
    },
    {
      "deviceDtTm": "2000-08-27 02:34:29",
      "glucose": 111
    },
    {
      "deviceDtTm": "2000-08-27 02:44:31",
      "glucose": 111
    },
    {
      "deviceDtTm": "2000-08-27 02:54:37",
      "glucose": 117
    },
    {
      "deviceDtTm": "2000-08-27 03:04:31",
      "glucose": 122
    },
    {
      "deviceDtTm": "2000-08-27 03:14:35",
      "glucose": 123
    },
    {
      "deviceDtTm": "2000-08-27 03:24:39",
      "glucose": 121
    },
    {
      "deviceDtTm": "2000-08-27 03:34:39",
      "glucose": 119
    },
    {
      "deviceDtTm": "2000-08-27 03:44:42",
      "glucose": 118
    },
    {
      "deviceDtTm": "2000-08-27 03:54:38",
      "glucose": 119
    },
    {
      "deviceDtTm": "2000-08-27 04:04:35",
      "glucose": 119
    },
    {
      "deviceDtTm": "2000-08-27 04:14:42",
      "glucose": 115
    },
    {
      "deviceDtTm": "2000-08-27 04:24:42",
      "glucose": 113
    },
    {
      "deviceDtTm": "2000-08-27 04:34:39",
      "glucose": 108
    },
    {
      "deviceDtTm": "2000-08-27 04:44:44",
      "glucose": 111
    },
    {
      "deviceDtTm": "2000-08-27 04:54:43",
      "glucose": 100
    },
    {
      "deviceDtTm": "2000-08-27 05:04:42",
      "glucose": 93
    },
    {
      "deviceDtTm": "2000-08-27 05:14:40",
      "glucose": 94
    },
    {
      "deviceDtTm": "2000-08-27 05:24:46",
      "glucose": 95
    },
    {
      "deviceDtTm": "2000-08-27 05:34:45",
      "glucose": 79
    },
    {
      "deviceDtTm": "2000-08-27 05:44:46",
      "glucose": 77
    },
    {
      "deviceDtTm": "2000-08-27 05:54:42",
      "glucose": 82
    },
    {
      "deviceDtTm": "2000-08-27 06:04:42",
      "glucose": 79
    },
    {
      "deviceDtTm": "2000-08-27 06:14:45",
      "glucose": 70
    },
    {
      "deviceDtTm": "2000-08-27 06:24:47",
      "glucose": 72
    },
    {
      "deviceDtTm": "2000-08-27 06:34:50",
      "glucose": 70
    },
    {
      "deviceDtTm": "2000-08-27 06:44:51",
      "glucose": 62
    },
    {
      "deviceDtTm": "2000-08-27 06:54:49",
      "glucose": 62
    },
    {
      "deviceDtTm": "2000-08-27 07:04:54",
      "glucose": 58
    },
    {
      "deviceDtTm": "2000-08-27 07:14:48",
      "glucose": 55
    },
    {
      "deviceDtTm": "2000-08-27 07:24:53",
      "glucose": 55
    },
    {
      "deviceDtTm": "2000-08-27 07:34:47",
      "glucose": 55
    },
    {
      "deviceDtTm": "2000-08-27 07:44:51",
      "glucose": 56
    },
    {
      "deviceDtTm": "2000-08-27 07:54:57",
      "glucose": 60
    },
    {
      "deviceDtTm": "2000-08-27 08:04:51",
      "glucose": 62
    },
    {
      "deviceDtTm": "2000-08-27 08:14:53",
      "glucose": 65
    },
    {
      "deviceDtTm": "2000-08-27 08:24:52",
      "glucose": 68
    },
    {
      "deviceDtTm": "2000-08-27 08:34:55",
      "glucose": 76
    },
    {
      "deviceDtTm": "2000-08-27 08:44:54",
      "glucose": 90
    },
    {
      "deviceDtTm": "2000-08-27 08:54:57",
      "glucose": 103
    },
    {
      "deviceDtTm": "2000-08-27 09:04:59",
      "glucose": 122
    },
    {
      "deviceDtTm": "2000-08-27 09:14:58",
      "glucose": 128
    },
    {
      "deviceDtTm": "2000-08-27 09:24:56",
      "glucose": 130
    },
    {
      "deviceDtTm": "2000-08-27 09:35:01",
      "glucose": 138
    },
    {
      "deviceDtTm": "2000-08-27 09:44:56",
      "glucose": 144
    },
    {
      "deviceDtTm": "2000-08-27 09:55:00",
      "glucose": 149
    },
    {
      "deviceDtTm": "2000-08-27 10:05:00",
      "glucose": 157
    },
    {
      "deviceDtTm": "2000-08-27 10:15:01",
      "glucose": 165
    },
    {
      "deviceDtTm": "2000-08-27 10:25:00",
      "glucose": 172
    },
    {
      "deviceDtTm": "2000-08-27 10:34:59",
      "glucose": 181
    },
    {
      "deviceDtTm": "2000-08-27 10:45:02",
      "glucose": 181
    },
    {
      "deviceDtTm": "2000-08-27 10:55:00",
      "glucose": 184
    },
    {
      "deviceDtTm": "2000-08-27 11:05:05",
      "glucose": 189
    },
    {
      "deviceDtTm": "2000-08-27 11:15:07",
      "glucose": 191
    },
    {
      "deviceDtTm": "2000-08-27 11:25:05",
      "glucose": 187
    },
    {
      "deviceDtTm": "2000-08-27 11:35:03",
      "glucose": 187
    },
    {
      "deviceDtTm": "2000-08-27 11:45:01",
      "glucose": 187
    },
    {
      "deviceDtTm": "2000-08-27 11:55:03",
      "glucose": 186
    },
    {
      "deviceDtTm": "2000-08-27 12:05:08",
      "glucose": 184
    },
    {
      "deviceDtTm": "2000-08-27 12:15:12",
      "glucose": 184
    },
    {
      "deviceDtTm": "2000-08-27 12:25:05",
      "glucose": 182
    },
    {
      "deviceDtTm": "2000-08-27 12:35:13",
      "glucose": 181
    },
    {
      "deviceDtTm": "2000-08-27 12:45:06",
      "glucose": 181
    },
    {
      "deviceDtTm": "2000-08-27 12:55:11",
      "glucose": 184
    },
    {
      "deviceDtTm": "2000-08-27 13:05:11",
      "glucose": 190
    },
    {
      "deviceDtTm": "2000-08-27 13:15:08",
      "glucose": 200
    },
    {
      "deviceDtTm": "2000-08-27 13:25:07",
      "glucose": 205
    },
    {
      "deviceDtTm": "2000-08-27 13:35:13",
      "glucose": 195
    },
    {
      "deviceDtTm": "2000-08-27 13:45:12",
      "glucose": 177
    },
    {
      "deviceDtTm": "2000-08-27 13:55:18",
      "glucose": 168
    },
    {
      "deviceDtTm": "2000-08-27 14:05:12",
      "glucose": 158
    },
    {
      "deviceDtTm": "2000-08-27 14:15:14",
      "glucose": 157
    },
    {
      "deviceDtTm": "2000-08-27 14:25:16",
      "glucose": 147
    },
    {
      "deviceDtTm": "2000-08-27 14:35:14",
      "glucose": 139
    },
    {
      "deviceDtTm": "2000-08-27 14:45:21",
      "glucose": 138
    },
    {
      "deviceDtTm": "2000-08-27 14:55:12",
      "glucose": 132
    },
    {
      "deviceDtTm": "2000-08-27 15:05:14",
      "glucose": 125
    },
    {
      "deviceDtTm": "2000-08-27 15:15:19",
      "glucose": 113
    },
    {
      "deviceDtTm": "2000-08-27 15:25:21",
      "glucose": 104
    },
    {
      "deviceDtTm": "2000-08-27 15:35:15",
      "glucose": 98
    },
    {
      "deviceDtTm": "2000-08-27 15:45:15",
      "glucose": 91
    },
    {
      "deviceDtTm": "2000-08-27 15:55:16",
      "glucose": 86
    },
    {
      "deviceDtTm": "2000-08-27 16:05:22",
      "glucose": 81
    },
    {
      "deviceDtTm": "2000-08-27 16:15:24",
      "glucose": 80
    },
    {
      "deviceDtTm": "2000-08-27 16:25:18",
      "glucose": 77
    },
    {
      "deviceDtTm": "2000-08-27 16:35:24",
      "glucose": 74
    },
    {
      "deviceDtTm": "2000-08-27 16:45:26",
      "glucose": 74
    },
    {
      "deviceDtTm": "2000-08-27 16:55:24",
      "glucose": 75
    },
    {
      "deviceDtTm": "2000-08-27 17:05:24",
      "glucose": 75
    },
    {
      "deviceDtTm": "2000-08-27 17:15:25",
      "glucose": 77
    },
    {
      "deviceDtTm": "2000-08-27 17:25:30",
      "glucose": 78
    },
    {
      "deviceDtTm": "2000-08-27 17:35:22",
      "glucose": 80
    },
    {
      "deviceDtTm": "2000-08-27 17:45:29",
      "glucose": 82
    },
    {
      "deviceDtTm": "2000-08-27 17:55:28",
      "glucose": 83
    },
    {
      "deviceDtTm": "2000-08-27 18:05:29",
      "glucose": 88
    },
    {
      "deviceDtTm": "2000-08-27 18:15:24",
      "glucose": 88
    },
    {
      "deviceDtTm": "2000-08-27 18:25:30",
      "glucose": 88
    },
    {
      "deviceDtTm": "2000-08-27 18:35:34",
      "glucose": 102
    },
    {
      "deviceDtTm": "2000-08-27 18:45:33",
      "glucose": 110
    },
    {
      "deviceDtTm": "2000-08-27 18:55:34",
      "glucose": 102
    },
    {
      "deviceDtTm": "2000-08-27 19:05:30",
      "glucose": 87
    },
    {
      "deviceDtTm": "2000-08-27 19:15:33",
      "glucose": 88
    },
    {
      "deviceDtTm": "2000-08-27 19:25:31",
      "glucose": 91
    },
    {
      "deviceDtTm": "2000-08-27 19:35:37",
      "glucose": 91
    },
    {
      "deviceDtTm": "2000-08-27 19:45:35",
      "glucose": 87
    },
    {
      "deviceDtTm": "2000-08-27 19:55:30",
      "glucose": 80
    },
    {
      "deviceDtTm": "2000-08-27 20:05:32",
      "glucose": 80
    },
    {
      "deviceDtTm": "2000-08-27 20:15:40",
      "glucose": 77
    },
    {
      "deviceDtTm": "2000-08-27 20:25:31",
      "glucose": 77
    },
    {
      "deviceDtTm": "2000-08-27 20:35:35",
      "glucose": 82
    },
    {
      "deviceDtTm": "2000-08-27 20:45:35",
      "glucose": 86
    },
    {
      "deviceDtTm": "2000-08-27 20:55:35",
      "glucose": 96
    },
    {
      "deviceDtTm": "2000-08-27 21:05:37",
      "glucose": 105
    },
    {
      "deviceDtTm": "2000-08-27 21:15:41",
      "glucose": 112
    },
    {
      "deviceDtTm": "2000-08-27 21:25:44",
      "glucose": 120
    },
    {
      "deviceDtTm": "2000-08-27 21:35:39",
      "glucose": 128
    },
    {
      "deviceDtTm": "2000-08-27 21:45:44",
      "glucose": 127
    },
    {
      "deviceDtTm": "2000-08-27 21:55:39",
      "glucose": 131
    },
    {
      "deviceDtTm": "2000-08-27 22:05:45",
      "glucose": 140
    },
    {
      "deviceDtTm": "2000-08-27 22:15:41",
      "glucose": 147
    },
    {
      "deviceDtTm": "2000-08-27 22:25:41",
      "glucose": 159
    },
    {
      "deviceDtTm": "2000-08-27 22:35:47",
      "glucose": 164
    },
    {
      "deviceDtTm": "2000-08-27 22:45:39",
      "glucose": 166
    },
    {
      "deviceDtTm": "2000-08-27 22:55:48",
      "glucose": 167
    },
    {
      "deviceDtTm": "2000-08-27 23:05:45",
      "glucose": 170
    },
    {
      "deviceDtTm": "2000-08-27 23:15:41",
      "glucose": 170
    },
    {
      "deviceDtTm": "2000-08-27 23:25:50",
      "glucose": 171
    },
    {
      "deviceDtTm": "2000-08-27 23:35:48",
      "glucose": 172
    },
    {
      "deviceDtTm": "2000-08-27 23:45:48",
      "glucose": 172
    },
    {
      "deviceDtTm": "2000-08-27 23:55:44",
      "glucose": 173
    },
    {
      "deviceDtTm": "2000-08-28 00:05:45",
      "glucose": 176
    },
    {
      "deviceDtTm": "2000-08-28 00:15:51",
      "glucose": 176
    },
    {
      "deviceDtTm": "2000-08-28 00:25:45",
      "glucose": 174
    },
    {
      "deviceDtTm": "2000-08-28 00:35:49",
      "glucose": 173
    },
    {
      "deviceDtTm": "2000-08-28 00:45:53",
      "glucose": 171
    },
    {
      "deviceDtTm": "2000-08-28 00:55:53",
      "glucose": 158
    },
    {
      "deviceDtTm": "2000-08-28 01:05:57",
      "glucose": 166
    },
    {
      "deviceDtTm": "2000-08-28 01:15:52",
      "glucose": 168
    },
    {
      "deviceDtTm": "2000-08-28 01:25:49",
      "glucose": 165
    },
    {
      "deviceDtTm": "2000-08-28 01:35:57",
      "glucose": 165
    },
    {
      "deviceDtTm": "2000-08-28 01:45:56",
      "glucose": 170
    },
    {
      "deviceDtTm": "2000-08-28 01:55:53",
      "glucose": 174
    },
    {
      "deviceDtTm": "2000-08-28 02:05:59",
      "glucose": 174
    },
    {
      "deviceDtTm": "2000-08-28 02:15:57",
      "glucose": 173
    },
    {
      "deviceDtTm": "2000-08-28 02:25:56",
      "glucose": 174
    },
    {
      "deviceDtTm": "2000-08-28 02:35:54",
      "glucose": 177
    },
    {
      "deviceDtTm": "2000-08-28 02:46:00",
      "glucose": 185
    },
    {
      "deviceDtTm": "2000-08-28 02:55:59",
      "glucose": 184
    },
    {
      "deviceDtTm": "2000-08-28 03:06:00",
      "glucose": 177
    },
    {
      "deviceDtTm": "2000-08-28 03:15:56",
      "glucose": 177
    },
    {
      "deviceDtTm": "2000-08-28 03:25:56",
      "glucose": 175
    },
    {
      "deviceDtTm": "2000-08-28 03:35:59",
      "glucose": 175
    },
    {
      "deviceDtTm": "2000-08-28 03:46:01",
      "glucose": 177
    },
    {
      "deviceDtTm": "2000-08-28 03:56:04",
      "glucose": 180
    },
    {
      "deviceDtTm": "2000-08-28 04:06:05",
      "glucose": 183
    },
    {
      "deviceDtTm": "2000-08-28 04:16:03",
      "glucose": 181
    },
    {
      "deviceDtTm": "2000-08-28 04:26:08",
      "glucose": 179
    },
    {
      "deviceDtTm": "2000-08-28 04:36:02",
      "glucose": 178
    },
    {
      "deviceDtTm": "2000-08-28 04:46:07",
      "glucose": 178
    },
    {
      "deviceDtTm": "2000-08-28 04:56:01",
      "glucose": 176
    },
    {
      "deviceDtTm": "2000-08-28 05:06:05",
      "glucose": 175
    },
    {
      "deviceDtTm": "2000-08-28 05:16:11",
      "glucose": 176
    },
    {
      "deviceDtTm": "2000-08-28 05:26:05",
      "glucose": 175
    },
    {
      "deviceDtTm": "2000-08-28 05:36:07",
      "glucose": 174
    },
    {
      "deviceDtTm": "2000-08-28 05:46:06",
      "glucose": 175
    },
    {
      "deviceDtTm": "2000-08-28 05:56:10",
      "glucose": 166
    },
    {
      "deviceDtTm": "2000-08-28 06:06:08",
      "glucose": 159
    },
    {
      "deviceDtTm": "2000-08-28 06:16:12",
      "glucose": 156
    },
    {
      "deviceDtTm": "2000-08-28 06:26:13",
      "glucose": 162
    },
    {
      "deviceDtTm": "2000-08-28 06:36:12",
      "glucose": 164
    },
    {
      "deviceDtTm": "2000-08-28 06:46:10",
      "glucose": 164
    },
    {
      "deviceDtTm": "2000-08-28 06:56:15",
      "glucose": 165
    },
    {
      "deviceDtTm": "2000-08-28 07:06:10",
      "glucose": 167
    },
    {
      "deviceDtTm": "2000-08-28 07:16:15",
      "glucose": 162
    },
    {
      "deviceDtTm": "2000-08-28 07:26:14",
      "glucose": 154
    },
    {
      "deviceDtTm": "2000-08-28 07:36:15",
      "glucose": 153
    },
    {
      "deviceDtTm": "2000-08-28 07:46:14",
      "glucose": 149
    },
    {
      "deviceDtTm": "2000-08-28 07:56:13",
      "glucose": 146
    },
    {
      "deviceDtTm": "2000-08-28 08:06:16",
      "glucose": 143
    },
    {
      "deviceDtTm": "2000-08-28 08:16:14",
      "glucose": 139
    },
    {
      "deviceDtTm": "2000-08-28 08:26:19",
      "glucose": 132
    },
    {
      "deviceDtTm": "2000-08-28 08:36:21",
      "glucose": 131
    },
    {
      "deviceDtTm": "2000-08-28 08:46:19",
      "glucose": 127
    },
    {
      "deviceDtTm": "2000-08-28 08:56:17",
      "glucose": 122
    },
    {
      "deviceDtTm": "2000-08-28 09:06:15",
      "glucose": 121
    },
    {
      "deviceDtTm": "2000-08-28 09:16:17",
      "glucose": 122
    },
    {
      "deviceDtTm": "2000-08-28 09:26:22",
      "glucose": 129
    },
    {
      "deviceDtTm": "2000-08-28 09:36:26",
      "glucose": 137
    },
    {
      "deviceDtTm": "2000-08-28 09:46:19",
      "glucose": 141
    },
    {
      "deviceDtTm": "2000-08-28 09:56:27",
      "glucose": 134
    },
    {
      "deviceDtTm": "2000-08-28 10:06:20",
      "glucose": 128
    },
    {
      "deviceDtTm": "2000-08-28 10:16:25",
      "glucose": 120
    },
    {
      "deviceDtTm": "2000-08-28 10:26:26",
      "glucose": 115
    },
    {
      "deviceDtTm": "2000-08-28 10:36:22",
      "glucose": 111
    },
    {
      "deviceDtTm": "2000-08-28 10:46:21",
      "glucose": 104
    },
    {
      "deviceDtTm": "2000-08-28 10:56:27",
      "glucose": 99
    },
    {
      "deviceDtTm": "2000-08-28 11:06:27",
      "glucose": 96
    },
    {
      "deviceDtTm": "2000-08-28 11:16:32",
      "glucose": 106
    },
    {
      "deviceDtTm": "2000-08-28 11:26:26",
      "glucose": 131
    },
    {
      "deviceDtTm": "2000-08-28 11:36:29",
      "glucose": 152
    },
    {
      "deviceDtTm": "2000-08-28 11:46:30",
      "glucose": 160
    },
    {
      "deviceDtTm": "2000-08-28 11:56:29",
      "glucose": 182
    },
    {
      "deviceDtTm": "2000-08-28 12:06:35",
      "glucose": 197
    },
    {
      "deviceDtTm": "2000-08-28 12:16:26",
      "glucose": 203
    },
    {
      "deviceDtTm": "2000-08-28 12:26:28",
      "glucose": 206
    },
    {
      "deviceDtTm": "2000-08-28 12:36:33",
      "glucose": 219
    },
    {
      "deviceDtTm": "2000-08-28 12:46:35",
      "glucose": 218
    },
    {
      "deviceDtTm": "2000-08-28 12:56:29",
      "glucose": 199
    },
    {
      "deviceDtTm": "2000-08-28 13:06:30",
      "glucose": 173
    },
    {
      "deviceDtTm": "2000-08-28 13:16:31",
      "glucose": 151
    },
    {
      "deviceDtTm": "2000-08-28 13:26:36",
      "glucose": 133
    },
    {
      "deviceDtTm": "2000-08-28 13:36:38",
      "glucose": 123
    },
    {
      "deviceDtTm": "2000-08-28 13:46:32",
      "glucose": 121
    },
    {
      "deviceDtTm": "2000-08-28 13:56:38",
      "glucose": 121
    },
    {
      "deviceDtTm": "2000-08-28 14:06:40",
      "glucose": 119
    },
    {
      "deviceDtTm": "2000-08-28 14:16:38",
      "glucose": 130
    },
    {
      "deviceDtTm": "2000-08-28 14:26:38",
      "glucose": 138
    },
    {
      "deviceDtTm": "2000-08-28 14:36:39",
      "glucose": 152
    },
    {
      "deviceDtTm": "2000-08-28 14:46:44",
      "glucose": 162
    },
    {
      "deviceDtTm": "2000-08-28 14:56:36",
      "glucose": 158
    },
    {
      "deviceDtTm": "2000-08-28 15:06:43",
      "glucose": 159
    },
    {
      "deviceDtTm": "2000-08-28 15:16:42",
      "glucose": 160
    },
    {
      "deviceDtTm": "2000-08-28 15:26:43",
      "glucose": 160
    },
    {
      "deviceDtTm": "2000-08-28 15:36:38",
      "glucose": 169
    },
    {
      "deviceDtTm": "2000-08-28 15:46:44",
      "glucose": 182
    },
    {
      "deviceDtTm": "2000-08-28 15:56:48",
      "glucose": 187
    },
    {
      "deviceDtTm": "2000-08-28 16:06:47",
      "glucose": 187
    },
    {
      "deviceDtTm": "2000-08-28 16:16:48",
      "glucose": 193
    },
    {
      "deviceDtTm": "2000-08-28 16:26:44",
      "glucose": 202
    },
    {
      "deviceDtTm": "2000-08-28 16:36:47",
      "glucose": 205
    },
    {
      "deviceDtTm": "2000-08-28 16:46:45",
      "glucose": 211
    },
    {
      "deviceDtTm": "2000-08-28 16:56:51",
      "glucose": 225
    },
    {
      "deviceDtTm": "2000-08-28 17:06:49",
      "glucose": 245
    },
    {
      "deviceDtTm": "2000-08-28 17:16:44",
      "glucose": 253
    },
    {
      "deviceDtTm": "2000-08-28 17:26:46",
      "glucose": 265
    },
    {
      "deviceDtTm": "2000-08-28 17:36:54",
      "glucose": 275
    },
    {
      "deviceDtTm": "2000-08-28 17:46:45",
      "glucose": 275
    },
    {
      "deviceDtTm": "2000-08-28 17:56:49",
      "glucose": 279
    },
    {
      "deviceDtTm": "2000-08-28 18:06:49",
      "glucose": 282
    },
    {
      "deviceDtTm": "2000-08-28 18:16:49",
      "glucose": 283
    },
    {
      "deviceDtTm": "2000-08-28 18:26:51",
      "glucose": 284
    },
    {
      "deviceDtTm": "2000-08-28 18:36:55",
      "glucose": 275
    },
    {
      "deviceDtTm": "2000-08-28 18:46:58",
      "glucose": 273
    },
    {
      "deviceDtTm": "2000-08-28 19:27:00",
      "glucose": 140
    },
    {
      "deviceDtTm": "2000-08-28 19:36:55",
      "glucose": 99
    },
    {
      "deviceDtTm": "2000-08-28 19:46:55",
      "glucose": 79
    },
    {
      "deviceDtTm": "2000-08-28 19:57:01",
      "glucose": 70
    },
    {
      "deviceDtTm": "2000-08-28 20:06:54",
      "glucose": 61
    },
    {
      "deviceDtTm": "2000-08-28 20:17:02",
      "glucose": 54
    },
    {
      "deviceDtTm": "2000-08-28 20:26:59",
      "glucose": 63
    },
    {
      "deviceDtTm": "2000-08-28 20:36:56",
      "glucose": 69
    },
    {
      "deviceDtTm": "2000-08-28 20:47:04",
      "glucose": 73
    },
    {
      "deviceDtTm": "2000-08-28 20:57:02",
      "glucose": 70
    },
    {
      "deviceDtTm": "2000-08-28 21:07:02",
      "glucose": 67
    },
    {
      "deviceDtTm": "2000-08-28 21:16:58",
      "glucose": 67
    },
    {
      "deviceDtTm": "2000-08-28 21:26:59",
      "glucose": 67
    },
    {
      "deviceDtTm": "2000-08-28 21:37:05",
      "glucose": 65
    },
    {
      "deviceDtTm": "2000-08-28 21:46:59",
      "glucose": 61
    },
    {
      "deviceDtTm": "2000-08-28 21:57:03",
      "glucose": 60
    },
    {
      "deviceDtTm": "2000-08-28 22:07:07",
      "glucose": 55
    },
    {
      "deviceDtTm": "2000-08-28 22:17:07",
      "glucose": 55
    },
    {
      "deviceDtTm": "2000-08-28 22:27:11",
      "glucose": 53
    },
    {
      "deviceDtTm": "2000-08-28 22:37:06",
      "glucose": 54
    },
    {
      "deviceDtTm": "2000-08-28 22:47:03",
      "glucose": 53
    },
    {
      "deviceDtTm": "2000-08-28 22:57:11",
      "glucose": 55
    },
    {
      "deviceDtTm": "2000-08-28 23:07:10",
      "glucose": 56
    },
    {
      "deviceDtTm": "2000-08-28 23:17:07",
      "glucose": 57
    },
    {
      "deviceDtTm": "2000-08-28 23:27:13",
      "glucose": 70
    },
    {
      "deviceDtTm": "2000-08-28 23:37:11",
      "glucose": 103
    },
    {
      "deviceDtTm": "2000-08-28 23:47:10",
      "glucose": 109
    },
    {
      "deviceDtTm": "2000-08-28 23:57:09",
      "glucose": 127
    },
    {
      "deviceDtTm": "2000-08-29 00:07:14",
      "glucose": 132
    },
    {
      "deviceDtTm": "2000-08-29 00:17:13",
      "glucose": 133
    },
    {
      "deviceDtTm": "2000-08-29 00:27:14",
      "glucose": 126
    },
    {
      "deviceDtTm": "2000-08-29 00:37:10",
      "glucose": 98
    },
    {
      "deviceDtTm": "2000-08-29 00:47:10",
      "glucose": 97
    },
    {
      "deviceDtTm": "2000-08-29 00:57:13",
      "glucose": 86
    },
    {
      "deviceDtTm": "2000-08-29 01:07:15",
      "glucose": 81
    },
    {
      "deviceDtTm": "2000-08-29 01:17:18",
      "glucose": 112
    },
    {
      "deviceDtTm": "2000-08-29 01:27:19",
      "glucose": 136
    },
    {
      "deviceDtTm": "2000-08-29 01:37:18",
      "glucose": 143
    },
    {
      "deviceDtTm": "2000-08-29 01:47:22",
      "glucose": 147
    },
    {
      "deviceDtTm": "2000-08-29 01:57:16",
      "glucose": 155
    },
    {
      "deviceDtTm": "2000-08-29 02:07:21",
      "glucose": 163
    },
    {
      "deviceDtTm": "2000-08-29 02:17:15",
      "glucose": 165
    },
    {
      "deviceDtTm": "2000-08-29 02:27:19",
      "glucose": 180
    },
    {
      "deviceDtTm": "2000-08-29 02:37:25",
      "glucose": 178
    },
    {
      "deviceDtTm": "2000-08-29 02:47:19",
      "glucose": 199
    },
    {
      "deviceDtTm": "2000-08-29 02:57:21",
      "glucose": 205
    },
    {
      "deviceDtTm": "2000-08-29 03:07:20",
      "glucose": 211
    },
    {
      "deviceDtTm": "2000-08-29 03:17:24",
      "glucose": 211
    },
    {
      "deviceDtTm": "2000-08-29 03:27:22",
      "glucose": 215
    },
    {
      "deviceDtTm": "2000-08-29 03:37:26",
      "glucose": 220
    },
    {
      "deviceDtTm": "2000-08-29 03:47:27",
      "glucose": 218
    },
    {
      "deviceDtTm": "2000-08-29 03:57:26",
      "glucose": 216
    },
    {
      "deviceDtTm": "2000-08-29 04:07:24",
      "glucose": 217
    },
    {
      "deviceDtTm": "2000-08-29 04:17:29",
      "glucose": 228
    },
    {
      "deviceDtTm": "2000-08-29 04:27:24",
      "glucose": 226
    },
    {
      "deviceDtTm": "2000-08-29 04:37:29",
      "glucose": 222
    },
    {
      "deviceDtTm": "2000-08-29 04:47:28",
      "glucose": 225
    },
    {
      "deviceDtTm": "2000-08-29 04:57:29",
      "glucose": 221
    },
    {
      "deviceDtTm": "2000-08-29 05:07:29",
      "glucose": 217
    },
    {
      "deviceDtTm": "2000-08-29 05:17:27",
      "glucose": 215
    },
    {
      "deviceDtTm": "2000-08-29 05:27:30",
      "glucose": 213
    },
    {
      "deviceDtTm": "2000-08-29 05:37:28",
      "glucose": 211
    },
    {
      "deviceDtTm": "2000-08-29 05:47:34",
      "glucose": 211
    },
    {
      "deviceDtTm": "2000-08-29 05:57:36",
      "glucose": 211
    },
    {
      "deviceDtTm": "2000-08-29 06:07:33",
      "glucose": 210
    },
    {
      "deviceDtTm": "2000-08-29 06:17:31",
      "glucose": 209
    },
    {
      "deviceDtTm": "2000-08-29 06:27:29",
      "glucose": 197
    },
    {
      "deviceDtTm": "2000-08-29 06:37:32",
      "glucose": 197
    },
    {
      "deviceDtTm": "2000-08-29 06:47:37",
      "glucose": 200
    },
    {
      "deviceDtTm": "2000-08-29 06:57:40",
      "glucose": 204
    },
    {
      "deviceDtTm": "2000-08-29 07:07:33",
      "glucose": 199
    },
    {
      "deviceDtTm": "2000-08-29 07:17:41",
      "glucose": 192
    },
    {
      "deviceDtTm": "2000-08-29 07:27:34",
      "glucose": 183
    },
    {
      "deviceDtTm": "2000-08-29 07:37:39",
      "glucose": 169
    },
    {
      "deviceDtTm": "2000-08-29 07:47:40",
      "glucose": 158
    },
    {
      "deviceDtTm": "2000-08-29 07:57:36",
      "glucose": 147
    },
    {
      "deviceDtTm": "2000-08-29 08:07:35",
      "glucose": 127
    },
    {
      "deviceDtTm": "2000-08-29 08:17:41",
      "glucose": 107
    },
    {
      "deviceDtTm": "2000-08-29 08:27:41",
      "glucose": 95
    },
    {
      "deviceDtTm": "2000-08-29 08:37:46",
      "glucose": 95
    },
    {
      "deviceDtTm": "2000-08-29 08:47:40",
      "glucose": 97
    },
    {
      "deviceDtTm": "2000-08-29 08:57:43",
      "glucose": 96
    },
    {
      "deviceDtTm": "2000-08-29 09:07:44",
      "glucose": 95
    },
    {
      "deviceDtTm": "2000-08-29 09:17:43",
      "glucose": 94
    },
    {
      "deviceDtTm": "2000-08-29 09:27:49",
      "glucose": 84
    },
    {
      "deviceDtTm": "2000-08-29 09:37:40",
      "glucose": 78
    },
    {
      "deviceDtTm": "2000-08-29 09:47:42",
      "glucose": 73
    },
    {
      "deviceDtTm": "2000-08-29 09:57:47",
      "glucose": 66
    },
    {
      "deviceDtTm": "2000-08-29 10:07:49",
      "glucose": 58
    },
    {
      "deviceDtTm": "2000-08-29 10:17:43",
      "glucose": 58
    },
    {
      "deviceDtTm": "2000-08-29 10:27:44",
      "glucose": 55
    },
    {
      "deviceDtTm": "2000-08-29 10:37:45",
      "glucose": 56
    },
    {
      "deviceDtTm": "2000-08-29 10:47:50",
      "glucose": 56
    },
    {
      "deviceDtTm": "2000-08-29 10:57:52",
      "glucose": 58
    },
    {
      "deviceDtTm": "2000-08-29 11:08:04",
      "glucose": 62
    },
    {
      "deviceDtTm": "2000-08-29 11:17:53",
      "glucose": 64
    },
    {
      "deviceDtTm": "2000-08-29 11:27:54",
      "glucose": 67
    },
    {
      "deviceDtTm": "2000-08-29 11:37:52",
      "glucose": 67
    },
    {
      "deviceDtTm": "2000-08-29 11:47:52",
      "glucose": 68
    },
    {
      "deviceDtTm": "2000-08-29 11:57:53",
      "glucose": 76
    },
    {
      "deviceDtTm": "2000-08-29 12:07:59",
      "glucose": 82
    },
    {
      "deviceDtTm": "2000-08-29 12:17:51",
      "glucose": 81
    },
    {
      "deviceDtTm": "2000-08-29 12:27:57",
      "glucose": 80
    },
    {
      "deviceDtTm": "2000-08-29 23:40:29",
      "glucose": 93
    },
    {
      "deviceDtTm": "2000-08-29 23:50:33",
      "glucose": 92
    },
    {
      "deviceDtTm": "2000-08-30 00:00:33",
      "glucose": 94
    },
    {
      "deviceDtTm": "2000-08-30 00:10:33",
      "glucose": 95
    },
    {
      "deviceDtTm": "2000-08-30 00:20:35",
      "glucose": 96
    },
    {
      "deviceDtTm": "2000-08-30 00:30:39",
      "glucose": 85
    },
    {
      "deviceDtTm": "2000-08-30 00:40:42",
      "glucose": 80
    },
    {
      "deviceDtTm": "2000-08-30 00:50:37",
      "glucose": 80
    },
    {
      "deviceDtTm": "2000-08-30 01:00:42",
      "glucose": 76
    },
    {
      "deviceDtTm": "2000-08-30 01:10:37",
      "glucose": 100
    },
    {
      "deviceDtTm": "2000-08-30 01:20:43",
      "glucose": 104
    },
    {
      "deviceDtTm": "2000-08-30 01:30:39",
      "glucose": 106
    },
    {
      "deviceDtTm": "2000-08-30 01:40:39",
      "glucose": 110
    },
    {
      "deviceDtTm": "2000-08-30 01:50:45",
      "glucose": 118
    },
    {
      "deviceDtTm": "2000-08-30 02:00:37",
      "glucose": 118
    },
    {
      "deviceDtTm": "2000-08-30 02:10:46",
      "glucose": 117
    },
    {
      "deviceDtTm": "2000-08-30 02:20:43",
      "glucose": 117
    },
    {
      "deviceDtTm": "2000-08-30 02:30:39",
      "glucose": 116
    },
    {
      "deviceDtTm": "2000-08-30 02:40:48",
      "glucose": 116
    },
    {
      "deviceDtTm": "2000-08-30 02:50:46",
      "glucose": 115
    },
    {
      "deviceDtTm": "2000-08-30 03:00:46",
      "glucose": 113
    },
    {
      "deviceDtTm": "2000-08-30 03:10:42",
      "glucose": 110
    },
    {
      "deviceDtTm": "2000-08-30 03:20:43",
      "glucose": 110
    },
    {
      "deviceDtTm": "2000-08-30 03:30:49",
      "glucose": 111
    },
    {
      "deviceDtTm": "2000-08-30 03:40:43",
      "glucose": 110
    },
    {
      "deviceDtTm": "2000-08-30 03:50:47",
      "glucose": 111
    },
    {
      "deviceDtTm": "2000-08-30 04:00:51",
      "glucose": 118
    },
    {
      "deviceDtTm": "2000-08-30 04:10:51",
      "glucose": 119
    },
    {
      "deviceDtTm": "2000-08-30 04:20:54",
      "glucose": 120
    },
    {
      "deviceDtTm": "2000-08-30 04:30:50",
      "glucose": 119
    },
    {
      "deviceDtTm": "2000-08-30 04:40:47",
      "glucose": 120
    },
    {
      "deviceDtTm": "2000-08-30 04:50:55",
      "glucose": 120
    },
    {
      "deviceDtTm": "2000-08-30 05:00:54",
      "glucose": 119
    },
    {
      "deviceDtTm": "2000-08-30 05:10:51",
      "glucose": 121
    },
    {
      "deviceDtTm": "2000-08-30 05:20:57",
      "glucose": 123
    },
    {
      "deviceDtTm": "2000-08-30 05:30:55",
      "glucose": 122
    },
    {
      "deviceDtTm": "2000-08-30 05:40:54",
      "glucose": 122
    },
    {
      "deviceDtTm": "2000-08-30 05:50:52",
      "glucose": 126
    },
    {
      "deviceDtTm": "2000-08-30 06:00:58",
      "glucose": 131
    },
    {
      "deviceDtTm": "2000-08-30 06:10:57",
      "glucose": 133
    },
    {
      "deviceDtTm": "2000-08-30 06:20:58",
      "glucose": 136
    },
    {
      "deviceDtTm": "2000-08-30 06:30:54",
      "glucose": 139
    },
    {
      "deviceDtTm": "2000-08-30 06:40:54",
      "glucose": 140
    },
    {
      "deviceDtTm": "2000-08-30 06:50:57",
      "glucose": 144
    },
    {
      "deviceDtTm": "2000-08-30 07:00:59",
      "glucose": 147
    },
    {
      "deviceDtTm": "2000-08-30 07:11:02",
      "glucose": 153
    },
    {
      "deviceDtTm": "2000-08-30 07:21:03",
      "glucose": 156
    },
    {
      "deviceDtTm": "2000-08-30 07:31:01",
      "glucose": 159
    },
    {
      "deviceDtTm": "2000-08-30 07:41:06",
      "glucose": 161
    },
    {
      "deviceDtTm": "2000-08-30 07:51:00",
      "glucose": 157
    },
    {
      "deviceDtTm": "2000-08-30 08:01:05",
      "glucose": 157
    },
    {
      "deviceDtTm": "2000-08-30 08:10:59",
      "glucose": 160
    },
    {
      "deviceDtTm": "2000-08-30 08:21:03",
      "glucose": 163
    },
    {
      "deviceDtTm": "2000-08-30 08:31:09",
      "glucose": 162
    },
    {
      "deviceDtTm": "2000-08-30 08:41:03",
      "glucose": 159
    },
    {
      "deviceDtTm": "2000-08-30 08:51:05",
      "glucose": 155
    },
    {
      "deviceDtTm": "2000-08-30 09:01:04",
      "glucose": 148
    },
    {
      "deviceDtTm": "2000-08-30 09:11:07",
      "glucose": 146
    },
    {
      "deviceDtTm": "2000-08-30 09:21:06",
      "glucose": 145
    },
    {
      "deviceDtTm": "2000-08-30 09:31:10",
      "glucose": 142
    },
    {
      "deviceDtTm": "2000-08-30 09:41:11",
      "glucose": 136
    },
    {
      "deviceDtTm": "2000-08-30 09:51:10",
      "glucose": 132
    },
    {
      "deviceDtTm": "2000-08-30 10:01:08",
      "glucose": 125
    },
    {
      "deviceDtTm": "2000-08-30 10:11:13",
      "glucose": 121
    },
    {
      "deviceDtTm": "2000-08-30 10:21:08",
      "glucose": 118
    },
    {
      "deviceDtTm": "2000-08-30 10:31:13",
      "glucose": 113
    },
    {
      "deviceDtTm": "2000-08-30 10:41:12",
      "glucose": 112
    },
    {
      "deviceDtTm": "2000-08-30 10:51:13",
      "glucose": 125
    },
    {
      "deviceDtTm": "2000-08-30 11:01:12",
      "glucose": 136
    },
    {
      "deviceDtTm": "2000-08-30 11:11:11",
      "glucose": 143
    },
    {
      "deviceDtTm": "2000-08-30 11:21:14",
      "glucose": 146
    },
    {
      "deviceDtTm": "2000-08-30 11:31:12",
      "glucose": 154
    },
    {
      "deviceDtTm": "2000-08-30 11:41:17",
      "glucose": 156
    },
    {
      "deviceDtTm": "2000-08-30 11:51:19",
      "glucose": 156
    },
    {
      "deviceDtTm": "2000-08-30 12:01:17",
      "glucose": 158
    },
    {
      "deviceDtTm": "2000-08-30 12:11:15",
      "glucose": 156
    },
    {
      "deviceDtTm": "2000-08-30 12:21:13",
      "glucose": 156
    },
    {
      "deviceDtTm": "2000-08-30 12:31:15",
      "glucose": 156
    },
    {
      "deviceDtTm": "2000-08-30 12:41:20",
      "glucose": 162
    },
    {
      "deviceDtTm": "2000-08-30 12:51:24",
      "glucose": 162
    },
    {
      "deviceDtTm": "2000-08-30 13:01:17",
      "glucose": 163
    },
    {
      "deviceDtTm": "2000-08-30 13:11:25",
      "glucose": 165
    },
    {
      "deviceDtTm": "2000-08-30 13:21:18",
      "glucose": 163
    },
    {
      "deviceDtTm": "2000-08-30 13:31:23",
      "glucose": 157
    },
    {
      "deviceDtTm": "2000-08-30 13:41:24",
      "glucose": 161
    },
    {
      "deviceDtTm": "2000-08-30 13:51:20",
      "glucose": 172
    },
    {
      "deviceDtTm": "2000-08-30 14:01:19",
      "glucose": 193
    },
    {
      "deviceDtTm": "2000-08-30 14:11:25",
      "glucose": 201
    },
    {
      "deviceDtTm": "2000-08-30 14:21:24",
      "glucose": 203
    },
    {
      "deviceDtTm": "2000-08-30 14:31:30",
      "glucose": 193
    },
    {
      "deviceDtTm": "2000-08-30 14:41:24",
      "glucose": 178
    },
    {
      "deviceDtTm": "2000-08-30 14:51:26",
      "glucose": 161
    },
    {
      "deviceDtTm": "2000-08-30 15:01:28",
      "glucose": 137
    },
    {
      "deviceDtTm": "2000-08-30 15:11:27",
      "glucose": 120
    },
    {
      "deviceDtTm": "2000-08-30 15:21:33",
      "glucose": 111
    },
    {
      "deviceDtTm": "2000-08-30 15:31:24",
      "glucose": 98
    },
    {
      "deviceDtTm": "2000-08-30 15:41:26",
      "glucose": 89
    },
    {
      "deviceDtTm": "2000-08-30 15:51:31",
      "glucose": 84
    },
    {
      "deviceDtTm": "2000-08-30 16:01:33",
      "glucose": 74
    },
    {
      "deviceDtTm": "2000-08-30 16:11:27",
      "glucose": 69
    },
    {
      "deviceDtTm": "2000-08-30 16:21:28",
      "glucose": 65
    },
    {
      "deviceDtTm": "2000-08-30 16:31:28",
      "glucose": 58
    },
    {
      "deviceDtTm": "2000-08-30 16:41:34",
      "glucose": 55
    },
    {
      "deviceDtTm": "2000-08-30 16:51:36",
      "glucose": 52
    },
    {
      "deviceDtTm": "2000-08-30 17:01:30",
      "glucose": 51
    },
    {
      "deviceDtTm": "2000-08-30 17:11:36",
      "glucose": 60
    },
    {
      "deviceDtTm": "2000-08-30 17:21:38",
      "glucose": 57
    },
    {
      "deviceDtTm": "2000-08-30 17:31:36",
      "glucose": 71
    },
    {
      "deviceDtTm": "2000-08-30 17:41:36",
      "glucose": 88
    },
    {
      "deviceDtTm": "2000-08-30 17:51:37",
      "glucose": 100
    },
    {
      "deviceDtTm": "2000-08-30 18:01:42",
      "glucose": 116
    },
    {
      "deviceDtTm": "2000-08-30 18:11:34",
      "glucose": 127
    },
    {
      "deviceDtTm": "2000-08-30 18:21:41",
      "glucose": 138
    },
    {
      "deviceDtTm": "2000-08-30 18:31:40",
      "glucose": 152
    },
    {
      "deviceDtTm": "2000-08-30 18:41:41",
      "glucose": 166
    },
    {
      "deviceDtTm": "2000-08-30 18:51:36",
      "glucose": 180
    },
    {
      "deviceDtTm": "2000-08-30 19:01:42",
      "glucose": 182
    },
    {
      "deviceDtTm": "2000-08-30 19:11:46",
      "glucose": 187
    },
    {
      "deviceDtTm": "2000-08-30 19:21:45",
      "glucose": 198
    },
    {
      "deviceDtTm": "2000-08-30 19:31:46",
      "glucose": 199
    },
    {
      "deviceDtTm": "2000-08-30 19:41:42",
      "glucose": 186
    },
    {
      "deviceDtTm": "2000-08-30 19:51:45",
      "glucose": 171
    },
    {
      "deviceDtTm": "2000-08-30 20:01:43",
      "glucose": 154
    },
    {
      "deviceDtTm": "2000-08-30 20:11:49",
      "glucose": 139
    },
    {
      "deviceDtTm": "2000-08-30 20:21:47",
      "glucose": 127
    },
    {
      "deviceDtTm": "2000-08-30 20:31:42",
      "glucose": 115
    },
    {
      "deviceDtTm": "2000-08-30 20:41:44",
      "glucose": 98
    },
    {
      "deviceDtTm": "2000-08-30 20:51:52",
      "glucose": 91
    },
    {
      "deviceDtTm": "2000-08-30 21:01:43",
      "glucose": 83
    },
    {
      "deviceDtTm": "2000-08-30 21:11:47",
      "glucose": 77
    },
    {
      "deviceDtTm": "2000-08-30 21:21:47",
      "glucose": 72
    },
    {
      "deviceDtTm": "2000-08-30 21:31:47",
      "glucose": 67
    },
    {
      "deviceDtTm": "2000-08-30 21:41:49",
      "glucose": 63
    },
    {
      "deviceDtTm": "2000-08-30 21:51:53",
      "glucose": 62
    },
    {
      "deviceDtTm": "2000-08-30 22:01:56",
      "glucose": 61
    },
    {
      "deviceDtTm": "2000-08-30 22:11:51",
      "glucose": 59
    },
    {
      "deviceDtTm": "2000-08-30 22:21:57",
      "glucose": 66
    },
    {
      "deviceDtTm": "2000-08-30 22:31:51",
      "glucose": 75
    },
    {
      "deviceDtTm": "2000-08-30 22:41:58",
      "glucose": 84
    },
    {
      "deviceDtTm": "2000-08-30 22:51:53",
      "glucose": 90
    },
    {
      "deviceDtTm": "2000-08-30 23:01:53",
      "glucose": 91
    },
    {
      "deviceDtTm": "2000-08-30 23:11:59",
      "glucose": 91
    },
    {
      "deviceDtTm": "2000-08-30 23:21:52",
      "glucose": 95
    },
    {
      "deviceDtTm": "2000-08-30 23:32:00",
      "glucose": 97
    },
    {
      "deviceDtTm": "2000-08-30 23:41:57",
      "glucose": 95
    },
    {
      "deviceDtTm": "2000-08-30 23:51:54",
      "glucose": 94
    },
    {
      "deviceDtTm": "2000-08-31 00:02:02",
      "glucose": 90
    },
    {
      "deviceDtTm": "2000-08-31 00:12:00",
      "glucose": 88
    },
    {
      "deviceDtTm": "2000-08-31 00:22:00",
      "glucose": 88
    },
    {
      "deviceDtTm": "2000-08-31 00:31:56",
      "glucose": 87
    },
    {
      "deviceDtTm": "2000-08-31 00:41:57",
      "glucose": 87
    },
    {
      "deviceDtTm": "2000-08-31 00:52:03",
      "glucose": 88
    },
    {
      "deviceDtTm": "2000-08-31 01:01:57",
      "glucose": 90
    },
    {
      "deviceDtTm": "2000-08-31 01:12:01",
      "glucose": 94
    },
    {
      "deviceDtTm": "2000-08-31 01:22:05",
      "glucose": 96
    },
    {
      "deviceDtTm": "2000-08-31 01:32:05",
      "glucose": 96
    },
    {
      "deviceDtTm": "2000-08-31 01:42:09",
      "glucose": 96
    },
    {
      "deviceDtTm": "2000-08-31 01:52:04",
      "glucose": 96
    },
    {
      "deviceDtTm": "2000-08-31 02:02:01",
      "glucose": 95
    },
    {
      "deviceDtTm": "2000-08-31 02:12:09",
      "glucose": 95
    },
    {
      "deviceDtTm": "2000-08-31 02:22:08",
      "glucose": 95
    },
    {
      "deviceDtTm": "2000-08-31 02:32:05",
      "glucose": 95
    },
    {
      "deviceDtTm": "2000-08-31 02:42:11",
      "glucose": 95
    },
    {
      "deviceDtTm": "2000-08-31 02:52:09",
      "glucose": 97
    },
    {
      "deviceDtTm": "2000-08-31 03:02:08",
      "glucose": 96
    },
    {
      "deviceDtTm": "2000-08-31 03:12:07",
      "glucose": 94
    },
    {
      "deviceDtTm": "2000-08-31 03:22:12",
      "glucose": 94
    },
    {
      "deviceDtTm": "2000-08-31 03:32:11",
      "glucose": 93
    },
    {
      "deviceDtTm": "2000-08-31 03:42:12",
      "glucose": 92
    },
    {
      "deviceDtTm": "2000-08-31 03:52:08",
      "glucose": 91
    },
    {
      "deviceDtTm": "2000-08-31 04:02:08",
      "glucose": 91
    },
    {
      "deviceDtTm": "2000-08-31 04:12:11",
      "glucose": 91
    },
    {
      "deviceDtTm": "2000-08-31 04:22:13",
      "glucose": 89
    },
    {
      "deviceDtTm": "2000-08-31 04:32:16",
      "glucose": 90
    },
    {
      "deviceDtTm": "2000-08-31 04:42:17",
      "glucose": 89
    },
    {
      "deviceDtTm": "2000-08-31 04:52:16",
      "glucose": 87
    },
    {
      "deviceDtTm": "2000-08-31 05:02:20",
      "glucose": 85
    },
    {
      "deviceDtTm": "2000-08-31 05:12:14",
      "glucose": 82
    },
    {
      "deviceDtTm": "2000-08-31 05:22:19",
      "glucose": 81
    },
    {
      "deviceDtTm": "2000-08-31 05:32:13",
      "glucose": 80
    },
    {
      "deviceDtTm": "2000-08-31 05:42:17",
      "glucose": 78
    },
    {
      "deviceDtTm": "2000-08-31 05:52:23",
      "glucose": 76
    },
    {
      "deviceDtTm": "2000-08-31 06:02:17",
      "glucose": 74
    },
    {
      "deviceDtTm": "2000-08-31 06:12:19",
      "glucose": 71
    },
    {
      "deviceDtTm": "2000-08-31 06:22:18",
      "glucose": 67
    },
    {
      "deviceDtTm": "2000-08-31 06:32:22",
      "glucose": 64
    },
    {
      "deviceDtTm": "2000-08-31 06:42:20",
      "glucose": 62
    },
    {
      "deviceDtTm": "2000-08-31 06:52:24",
      "glucose": 60
    },
    {
      "deviceDtTm": "2000-08-31 07:02:26",
      "glucose": 58
    },
    {
      "deviceDtTm": "2000-08-31 07:12:24",
      "glucose": 57
    },
    {
      "deviceDtTm": "2000-08-31 07:22:22",
      "glucose": 57
    },
    {
      "deviceDtTm": "2000-08-31 07:32:27",
      "glucose": 58
    },
    {
      "deviceDtTm": "2000-08-31 07:42:22",
      "glucose": 61
    },
    {
      "deviceDtTm": "2000-08-31 07:52:27",
      "glucose": 64
    },
    {
      "deviceDtTm": "2000-08-31 08:02:26",
      "glucose": 79
    },
    {
      "deviceDtTm": "2000-08-31 08:12:27",
      "glucose": 91
    },
    {
      "deviceDtTm": "2000-08-31 08:22:27",
      "glucose": 92
    },
    {
      "deviceDtTm": "2000-08-31 08:32:25",
      "glucose": 88
    },
    {
      "deviceDtTm": "2000-08-31 08:42:28",
      "glucose": 87
    },
    {
      "deviceDtTm": "2000-08-31 08:52:26",
      "glucose": 88
    },
    {
      "deviceDtTm": "2000-08-31 09:02:32",
      "glucose": 91
    },
    {
      "deviceDtTm": "2000-08-31 09:12:34",
      "glucose": 95
    },
    {
      "deviceDtTm": "2000-08-31 09:22:31",
      "glucose": 100
    },
    {
      "deviceDtTm": "2000-08-31 09:32:29",
      "glucose": 104
    },
    {
      "deviceDtTm": "2000-08-31 09:42:27",
      "glucose": 117
    },
    {
      "deviceDtTm": "2000-08-31 09:52:30",
      "glucose": 122
    },
    {
      "deviceDtTm": "2000-08-24 21:01:29",
      "glucose": 106
    },
    {
      "deviceDtTm": "2000-08-24 21:11:26",
      "glucose": 103
    },
    {
      "deviceDtTm": "2000-08-24 21:21:25",
      "glucose": 101
    },
    {
      "deviceDtTm": "2000-08-24 21:31:31",
      "glucose": 99
    },
    {
      "deviceDtTm": "2000-08-24 21:41:30",
      "glucose": 99
    },
    {
      "deviceDtTm": "2000-08-24 21:51:35",
      "glucose": 104
    },
    {
      "deviceDtTm": "2000-08-24 22:01:29",
      "glucose": 113
    },
    {
      "deviceDtTm": "2000-08-24 22:11:32",
      "glucose": 113
    },
    {
      "deviceDtTm": "2000-08-24 22:21:34",
      "glucose": 118
    },
    {
      "deviceDtTm": "2000-08-24 22:31:32",
      "glucose": 119
    },
    {
      "deviceDtTm": "2000-08-24 22:41:39",
      "glucose": 90
    },
    {
      "deviceDtTm": "2000-08-24 22:51:30",
      "glucose": 81
    },
    {
      "deviceDtTm": "2000-08-24 23:01:31",
      "glucose": 131
    },
    {
      "deviceDtTm": "2000-08-24 23:11:37",
      "glucose": 150
    },
    {
      "deviceDtTm": "2000-08-24 23:21:39",
      "glucose": 143
    },
    {
      "deviceDtTm": "2000-08-24 23:31:33",
      "glucose": 139
    },
    {
      "deviceDtTm": "2000-08-24 23:41:33",
      "glucose": 143
    },
    {
      "deviceDtTm": "2000-08-24 23:51:34",
      "glucose": 149
    },
    {
      "deviceDtTm": "2000-08-25 00:01:40",
      "glucose": 157
    },
    {
      "deviceDtTm": "2000-08-25 00:11:42",
      "glucose": 160
    },
    {
      "deviceDtTm": "2000-08-25 00:21:36",
      "glucose": 172
    },
    {
      "deviceDtTm": "2000-08-25 00:31:42",
      "glucose": 171
    },
    {
      "deviceDtTm": "2000-08-25 00:41:44",
      "glucose": 172
    },
    {
      "deviceDtTm": "2000-08-25 00:51:42",
      "glucose": 167
    },
    {
      "deviceDtTm": "2000-08-31 10:02:35",
      "glucose": 130
    },
    {
      "deviceDtTm": "2000-08-31 10:12:38",
      "glucose": 137
    },
    {
      "deviceDtTm": "2000-08-31 10:22:31",
      "glucose": 138
    },
    {
      "deviceDtTm": "2000-08-31 10:32:39",
      "glucose": 145
    }
  ]
}